progressiveai/__init__.py
progressiveai/chat.py
progressiveai/chatasync.py
progressiveai/complete.py
progressiveai/completeasync.py
progressiveai/exceptions.py
progressiveai-0.0.10.dist-info/LICENSE
progressiveai-0.0.10.dist-info/METADATA
progressiveai-0.0.10.dist-info/WHEEL
progressiveai-0.0.10.dist-info/top_level.txt
progressiveai-0.0.10.dist-info/RECORD
