Metadata-Version: 2.1
Name: progressiveai
Version: 0.0.10
Summary: "This repository contains the Python library for ProgressiveAI, a powerful tool for interacting with AI Models. The library provides a simple and intuitive interface for sending requests to ProgressiveAI's AI Models and processing their responses."
Home-page: https://progressiveai.org
Author: ProgressiveAI
Author-email: support@progressiveai.org
Project-URL: Source Code, https://github.com/ProgressiveAI/progressiveai-python
Classifier: Programming Language :: Python :: 3
Classifier: License :: OSI Approved :: Apache Software License
Classifier: Operating System :: OS Independent
Requires-Python: >=3.9
License-File: LICENSE
